circuit_monitoring/ass_6.v
module signal_monitor (
    input wire [3:0] signal_a,
    input wire [3:0] signal_b,
    input wire [1:0] mode_select,
    input wire clk,
    input wire reset,

    output reg [2:0] status_leds,
    output reg [3:0] control_out
);

    reg [1:0] test_cnt;
    reg [3:0] next_control;

    always @(*) begin
        status_leds  = 3'b000;
        next_control = 4'b0000;

        case (mode_select)

            2'b00: begin
                next_control = signal_a + signal_b;
                status_leds  = 3'b001;
            end

            2'b01: begin
                if (signal_a > signal_b) begin
                    next_control = signal_a - signal_b;
                    status_leds  = 3'b100;
                end else if (signal_a < signal_b) begin
                    next_control = signal_b - signal_a;
                    status_leds  = 3'b010;
                end else begin
                    next_control = 4'b0000;
                    status_leds  = 3'b001;
                end
            end

            2'b10: begin
                case (test_cnt)
                    2'd0: next_control = 4'd0;
                    2'd1: next_control = 4'd5;
                    2'd2: next_control = 4'd10;
                    2'd3: next_control = 4'd15;
                endcase
                status_leds = 3'b111;
            end

            2'b11: begin
                next_control = (signal_a + signal_b) >> 1;
                status_leds  = 3'b111;
            end

        endcase
    end

    always @(posedge clk or posedge reset) begin
        if (reset) begin
            control_out <= 4'b0000;
            test_cnt    <= 2'b00;
        end else begin
            control_out <= next_control;

            if (mode_select == 2'b10) test_cnt <= test_cnt + 1'b1;
            else test_cnt <= 2'b00;
        end
    end

endmodule

circuit_monitoring/ass_6_tb.v
module tb_signal_monitor;

    reg [3:0] signal_a, signal_b;
    reg [1:0] mode_select;
    reg clk, reset;

    wire [2:0] status_leds;
    wire [3:0] control_out;

    signal_monitor dut (
        .signal_a(signal_a),
        .signal_b(signal_b),
        .mode_select(mode_select),
        .clk(clk),
        .reset(reset),
        .status_leds(status_leds),
        .control_out(control_out)
    );

    always #5 clk = ~clk;

    initial begin
        $dumpfile("lab6.vcd");
        $dumpvars(0, tb_signal_monitor);

        $monitor(
            "clk = %b | reset = %b | mode_select = %b | signal_a = %b | signal_b = %b | status_leds = %b | control_out = %b",
            clk, reset, mode_select, signal_a, signal_b, status_leds,
            control_out);

        clk = 0;
        reset = 1;
        signal_a = 0;
        signal_b = 0;
        mode_select = 2'b00;

        #20 reset = 0;

        mode_select = 2'b00;
        signal_a = 4'd7;
        signal_b = 4'd3;
        #20;

        mode_select = 2'b01;
        signal_a = 4'd12;
        signal_b = 4'd5;
        #20;

        signal_a = 4'd3;
        signal_b = 4'd9;
        #20;

        mode_select = 2'b11;
        signal_a = 4'd10;
        signal_b = 4'd6;
        #20;

        mode_select = 2'b10;
        #80;

        $finish;
    end

endmodule

circuit_monitoring/lab6.vcd
$date
	Tue Feb 10 06:57:06 2026
$end
$version
	Icarus Verilog
$end
$timescale
	1s
$end
$scope module tb_signal_monitor $end
$var wire 3 ! status_leds [2:0] $end
$var wire 4 " control_out [3:0] $end
$var reg 1 # clk $end
$var reg 2 $ mode_select [1:0] $end
$var reg 1 % reset $end
$var reg 4 & signal_a [3:0] $end
$var reg 4 ' signal_b [3:0] $end
$scope module dut $end
$var wire 1 # clk $end
$var wire 2 ( mode_select [1:0] $end
$var wire 1 % reset $end
$var wire 4 ) signal_a [3:0] $end
$var wire 4 * signal_b [3:0] $end
$var reg 4 + control_out [3:0] $end
$var reg 4 , next_control [3:0] $end
$var reg 3 - status_leds [2:0] $end
$var reg 2 . test_cnt [1:0] $end
$upscope $end
$upscope $end
$enddefinitions $end
$comment Show the parameter values. $end
$dumpall
$end
#0
$dumpvars
b0 .
b1 -
b0 ,
b0 +
b0 *
b0 )
b0 (
b0 '
b0 &
1%
b0 $
0#
b0 "
b1 !
$end
#5
1#
#10
0#
#15
1#
#20
b1010 ,
b1 !
b1 -
0#
b11 '
b11 *
b111 &
b111 )
0%
#25
b1010 "
b1010 +
1#
#30
0#
#35
1#
#40
b111 ,
b100 !
b100 -
0#
b101 '
b101 *
b1100 &
b1100 )
b1 $
b1 (
#45
b111 "
b111 +
1#
#50
0#
#55
1#
#60
b110 ,
b10 !
b10 -
0#
b1001 '
b1001 *
b11 &
b11 )
#65
b110 "
b110 +
1#
#70
0#
#75
1#
#80
b0 ,
b111 !
b111 -
0#
b110 '
b110 *
b1010 &
b1010 )
b11 $
b11 (
#85
b0 "
b0 +
1#
#90
0#
#95
1#
#100
b111 !
b111 -
0#
b10 $
b10 (
#105
b101 ,
b111 !
b111 -
b1 .
1#
#110
0#
#115
b1010 ,
b111 !
b111 -
b10 .
b101 "
b101 +
1#
#120
0#
#125
b1111 ,
b111 !
b111 -
b11 .
b1010 "
b1010 +
1#
#130
0#
#135
b0 ,
b111 !
b111 -
b0 .
b1111 "
b1111 +
1#
#140
0#
#145
b101 ,
b111 !
b111 -
b1 .
b0 "
b0 +
1#
#150
0#
#155
b1010 ,
b111 !
b111 -
b10 .
b101 "
b101 +
1#
#160
0#
#165
b1111 ,
b111 !
b111 -
b11 .
b1010 "
b1010 +
1#
#170
0#
#175
b0 ,
b111 !
b111 -
b0 .
b1111 "
b1111 +
1#
