2_half_full_adder/full_adder.v
module half_adder(sum,carry,a,b);
input a,b;
output sum,carry;
assign sum = a ^ b;
assign carry = a & b;
endmodule

module full_adder(sum,carry,a,b,cin);
input a,b,cin;
output sum,carry;
wire sum1,carry1,carry2;
half_adder h1(sum1,carry1,a,b);
half_adder h2(sum,carry2,sum1,cin);
assign carry = carry1 | carry2;
endmodule

full_adder/full_adder_tb.v
module full_adder_tb;
reg a,b,cin;
wire sum,carry;
full_adder fa1(sum,carry,a,b,cin);
initial begin
    $dumpfile("dump.vcd");
    $dumpvars(0,full_adder_tb);
    $monitor("a=%b b=%b cin=%b sum=%b carry=%b",a,b,cin,sum,carry);
    a=0;b=0; cin=0; #10;
    a=0;b=1; cin=0; #10;              
    a=1;b=0; cin=0; #10;
    a=1;b=1; cin=0; #10;
    a=0;b=0; cin=1; #10;
    a=0;b=1; cin=1; #10;              
    a=1;b=0; cin=1; #10;
    a=1;b=1; cin=1; #10;

    $finish;

end
endmodule

2_half_full_adder/dump.vcd
$date
	Mon Dec 29 09:19:51 2025
$end
$version
	Icarus Verilog
$end
$timescale
	1s
$end
$scope module full_adder_tb $end
$var wire 1 ! sum $end
$var wire 1 " carry $end
$var reg 1 # a $end
$var reg 1 $ b $end
$var reg 1 % cin $end
$scope module fa1 $end
$var wire 1 # a $end
$var wire 1 $ b $end
$var wire 1 " carry $end
$var wire 1 % cin $end
$var wire 1 & sum1 $end
$var wire 1 ! sum $end
$var wire 1 ' carry2 $end
$var wire 1 ( carry1 $end
$scope module h1 $end
$var wire 1 # a $end
$var wire 1 $ b $end
$var wire 1 ( carry $end
$var wire 1 & sum $end
$upscope $end
$scope module h2 $end
$var wire 1 & a $end
$var wire 1 % b $end
$var wire 1 ' carry $end
$var wire 1 ! sum $end
$upscope $end
$upscope $end
$upscope $end
$enddefinitions $end
$comment Show the parameter values. $end
$dumpall
$end
#0
$dumpvars
0(
0'
0&
0%
0$
0#
0"
0!
$end
#10
1!
1&
1$
#20
0$
1#
#30
0!
1"
0&
1(
1$
#40
0"
1!
0(
1%
0$
0#
#50
1"
0!
1'
1&
1$
#60
0$
1#
#70
1!
0'
0&
1(
1$
