ripple_up_counter/design.v
module ripple_up_counter(clk, clear, q);
    input clk;
    input clear;
    output [3:0] q;
    reg [3:0] q;

    always @(negedge clk or posedge clear)
    begin
        if(clear)
            q[0] <= 1'b0;
        else
            q[0] <= ~q[0];
    end

    always @(negedge q[0] or posedge clear)
    begin
        if(clear)
            q[1] <= 1'b0;
        else
            q[1] <= ~q[1];
    end

    always @(negedge q[1] or posedge clear)
    begin
        if(clear)
            q[2] <= 1'b0;
        else
            q[2] <= ~q[2];
    end

    always @(negedge q[2] or posedge clear)
    begin
        if(clear)
            q[3] <= 1'b0;
        else
            q[3] <= ~q[3];
    end

endmodule

ripple_up_counter/tb.v
module ripple_tb;
     reg clk;
    reg clear;
     wire [3:0] q;

     ripple_up_counter uut (.clk(clk), .clear(clear), .q(q));

     always #5 clk = ~clk;

     initial begin
         clk = 1'b0;
        clear = 1'b0;

         #5 clear = 1'b1; // Assert reset
        #10 clear = 1'b0; // De-assert reset

         $monitor("Time=%0t | Clear=%0b | Clock=%0b | Count=%0d", $time, clear, clk, q);

         #200 $stop;  
    $finish;
    end

    
     initial begin
      $dumpfile("dump.vcd");
      $dumpvars(0, ripple_tb);
    end

endmodule

ripple_up_counter/dump.vcd
$date
	Wed Feb 18 19:57:56 2026
$end
$version
	Icarus Verilog
$end
$timescale
	1s
$end
$scope module ripple_tb $end
$var wire 4 ! q [3:0] $end
$var reg 1 " clear $end
$var reg 1 # clk $end
$scope module uut $end
$var wire 1 " clear $end
$var wire 1 # clk $end
$var reg 4 $ q [3:0] $end
$upscope $end
$upscope $end
$enddefinitions $end
$comment Show the parameter values. $end
$dumpall
$end
#0
$dumpvars
bx $
0#
0"
bx !
$end
#5
b0 !
b0 $
1"
1#
#10
0#
#15
1#
0"
#20
b1 !
b1 $
0#
#25
1#
#30
b10 !
b10 $
0#
#35
1#
#40
b11 !
b11 $
0#
#45
1#
#50
b100 !
b100 $
0#
#55
1#
#60
b101 !
b101 $
0#
#65
1#
#70
b110 !
b110 $
0#
#75
1#
#80
b111 !
b111 $
0#
#85
1#
#90
b1000 !
b1000 $
0#
#95
1#
#100
b1001 !
b1001 $
0#
#105
1#
#110
b1010 !
b1010 $
0#
#115
1#
#120
b1011 !
b1011 $
0#
#125
1#
#130
b1100 !
b1100 $
0#
#135
1#
#140
b1101 !
b1101 $
0#
#145
1#
#150
b1110 !
b1110 $
0#
#155
1#
#160
b1111 !
b1111 $
0#
#165
1#
#170
b0 !
b0 $
0#
#175
1#
#180
b1 !
b1 $
0#
#185
1#
#190
b10 !
b10 $
0#
#195
1#
#200
b11 !
b11 $
0#
#205
1#
#210
b100 !
b100 $
0#
