octal_bin_enc/oct_bin_enc.v
module octal_bin_enc(in,out);
input[7:0]in;
output[2:0]out;

assign out[2] = in[4]|in[5]|in[6]|in[7];
assign out[1] = in[1]|in[2]|in[6]|in[7];
assign out[0] = in[1]|in[5]|in[3]|in[7];

endmodule

octal_bin_enc/oct_bin_enc_tb.v
module octal_bin_enc_tb();
reg [7:0]in;
wire [2:0]out;

octal_bin_enc uut(in,out);

initial
begin

    $dumpfile("dump.vcd");
    $dumpvars(0,octal_bin_enc_tb);
    $monitor("in=%b out=%b",in,out);
    
in=8'b00000000; #10
in=8'b00000001; #10
in=8'b00000010; #10
in=8'b00000100; #10
in=8'b00001000; #10
in=8'b00010000; #10
in=8'b00100000; #10
in=8'b01000000; #10
in=8'b10000000; #10
$finish;
end
endmodule

octal_bin_enc/dump.vcd
$date
	Sat Jan 10 08:44:37 2026
$end
$version
	Icarus Verilog
$end
$timescale
	1s
$end
$scope module octal_bin_enc_tb $end
$var wire 3 ! out [2:0] $end
$var reg 8 " in [7:0] $end
$scope module uut $end
$var wire 8 # in [7:0] $end
$var wire 3 $ out [2:0] $end
$upscope $end
$upscope $end
$enddefinitions $end
$comment Show the parameter values. $end
$dumpall
$end
#0
$dumpvars
b0 $
b0 #
b0 "
b0 !
$end
#10
b1 "
b1 #
#20
b11 !
b11 $
b10 "
b10 #
#30
b10 !
b10 $
b100 "
b100 #
#40
b1 !
b1 $
b1000 "
b1000 #
#50
b100 !
b100 $
b10000 "
b10000 #
#60
b101 !
b101 $
b100000 "
b100000 #
#70
b110 !
b110 $
b1000000 "
b1000000 #
#80
b111 !
b111 $
b10000000 "
b10000000 #
