eight_enc/8_3_enc.v
module encoder(d,y);
input [7:0]d;
output [2:0]y;

assign y[0] = d[1]|d[3]|d[5]|d[7];
assign y[1] = d[2]|d[3]|d[6]|d[7];
assign y[2] = d[4]|d[5]|d[6]|d[7];
endmodule

eight_enc/8_3_enc_tb.v
module encoder_tb;
reg[7:0] d;
wire[2:0]y;

encoder uut(d,y);

initial begin
    $dumpfile("encoder.vcd");
    $dumpvars(0,encoder_tb);
    $monitor("d=%b y=%b",d,y);

    d = 8'b00000000;#10;
    d = 8'b00000010;#10;
    d = 8'b00000100;#10;
    d = 8'b00001000;#10;
    d = 8'b00010000;#10;
    d = 8'b00100000;#10;
    d = 8'b01000000;#10;
    d = 8'b10000000;#10;
 

    $finish;
end
endmodule

eight_enc/encoder.vcd
$date
	Tue Dec 30 10:20:58 2025
$end
$version
	Icarus Verilog
$end
$timescale
	1s
$end
$scope module encoder_tb $end
$var wire 3 ! y [2:0] $end
$var reg 8 " d [7:0] $end
$scope module uut $end
$var wire 8 # d [7:0] $end
$var wire 3 $ y [2:0] $end
$upscope $end
$upscope $end
$enddefinitions $end
$comment Show the parameter values. $end
$dumpall
$end
#0
$dumpvars
b0 $
b0 #
b0 "
b0 !
$end
#10
b1 !
b1 $
b10 "
b10 #
#20
b10 !
b10 $
b100 "
b100 #
#30
b11 !
b11 $
b1000 "
b1000 #
#40
b100 !
b100 $
b10000 "
b10000 #
#50
b101 !
b101 $
b100000 "
b100000 #
#60
b110 !
b110 $
b1000000 "
b1000000 #
#70
b111 !
b111 $
b10000000 "
b10000000 #
