up_down_counter/up_down_counter.v
module counter (
    input  wire        clk,        
    input  wire        aresetn,     
    input  wire        load,       
    input  wire [31:0] loaddata,    
    input  wire        en,          
    input  wire        updwn,        
    output reg  [31:0] count
);

     always @(posedge clk or negedge aresetn) begin
        if (!aresetn)
            count <= 32'b0;                
        else if (load)
            count <= loaddata;             
        else if (en) begin
            if (updwn)
                count <= count + 1;         
            else
                count <= count - 1;         
      end
      end

endmodule

up_down_counter/up_down_counter_tb.v
module tb_counter;

    reg         clk;
    reg         aresetn;
    reg         load;
    reg  [31:0] loaddata;
    reg         en;
    reg         updwn;
    wire [31:0] count;

     counter dut (
        .clk(clk),
        .aresetn(aresetn),
        .load(load),
        .loaddata(loaddata),
        .en(en),
        .updwn(updwn),
        .count(count)
    );

     always #5 clk = ~clk;

    initial begin
         clk      = 0;
        aresetn  = 0;
        load     = 0;
        loaddata = 32'h0;
        en       = 0;
        updwn    = 1;

         $dumpfile("counter.vcd");
        $dumpvars(0, tb_counter);

         $monitor("T=%0t | rstn=%b | load=%b | en=%b | updwn=%b | count=%h",
                  $time, aresetn, load, en, updwn, count);

         #3  aresetn = 0;
        #7  aresetn = 1;

         #10 load = 1;
            loaddata = 32'h0000_000A;
        #10 load = 0;

          #10 en = 1;
            updwn = 1;
        #50;

         updwn = 0;
        #50;

         en = 0;
        #20;

         load = 1;
        loaddata = 32'h0000_00FF;
        #10 load = 0;

         en = 1;
        updwn = 1;
        #30;

        $finish;
    end

endmodule

up_down_counter/counter.vcd
$date
	Wed Feb  4 20:03:59 2026
$end
$version
	Icarus Verilog
$end
$timescale
	1s
$end
$scope module tb_counter $end
$var wire 32 ! count [31:0] $end
$var reg 1 " aresetn $end
$var reg 1 # clk $end
$var reg 1 $ en $end
$var reg 1 % load $end
$var reg 32 & loaddata [31:0] $end
$var reg 1 ' updwn $end
$scope module dut $end
$var wire 1 " aresetn $end
$var wire 1 # clk $end
$var wire 1 $ en $end
$var wire 1 % load $end
$var wire 32 ( loaddata [31:0] $end
$var wire 1 ' updwn $end
$var reg 32 ) count [31:0] $end
$upscope $end
$upscope $end
$enddefinitions $end
$comment Show the parameter values. $end
$dumpall
$end
#0
$dumpvars
b0 )
b0 (
1'
b0 &
0%
0$
0#
0"
b0 !
$end
#5
1#
#10
0#
1"
#15
1#
#20
0#
b1010 &
b1010 (
1%
#25
b1010 !
b1010 )
1#
#30
0#
0%
#35
1#
#40
0#
1$
#45
b1011 !
b1011 )
1#
#50
0#
#55
b1100 !
b1100 )
1#
#60
0#
#65
b1101 !
b1101 )
1#
#70
0#
#75
b1110 !
b1110 )
1#
#80
0#
#85
b1111 !
b1111 )
1#
#90
0#
0'
#95
b1110 !
b1110 )
1#
#100
0#
#105
b1101 !
b1101 )
1#
#110
0#
#115
b1100 !
b1100 )
1#
#120
0#
#125
b1011 !
b1011 )
1#
#130
0#
#135
b1010 !
b1010 )
1#
#140
0#
0$
#145
1#
#150
0#
#155
1#
#160
0#
b11111111 &
b11111111 (
1%
#165
b11111111 !
b11111111 )
1#
#170
0#
1'
1$
0%
#175
b100000000 !
b100000000 )
1#
#180
0#
#185
b100000001 !
b100000001 )
1#
#190
0#
#195
b100000010 !
b100000010 )
1#
