up_down_counter/up_down_counter.v
module up_down_counter (
    input  wire       clk,
    input  wire       rst,      
    input  wire       up_down,  
    output reg [3:0]  count
);

always @(posedge clk) begin
    if (rst)
        count <= 4'b0000;
    else if (up_down)
        count <= count + 1'b1;   
    else
        count <= count - 1'b1;   
end

endmodule

up_down_counter/up_down_counter_tb.v
`timescale 1ns/1ps

module tb_up_down_counter;

    reg clk;
    reg rst;
    reg up_down;
    wire [3:0] count;

     up_down_counter dut (
        .clk(clk),
        .rst(rst),
        .up_down(up_down),
        .count(count)
    );

     always #5 clk = ~clk;

    initial begin

        $dumpfile("dump.vcd");
        $dumpvars(0,tb_up_down_counter);
        $monitor("clk = %b rst = %b up_down = %b count = %b",clk,rst,up_down,count);
         clk = 0;
        rst = 1;
        up_down = 1;

         #10 rst = 0;

         #50 up_down = 1;

         #50 up_down = 0;

         #50 $finish;
    end

endmodule

up_down_counter/dump.vcd
$date
	Thu Jan 22 20:39:22 2026
$end
$version
	Icarus Verilog
$end
$timescale
	1ps
$end
$scope module tb_up_down_counter $end
$var wire 4 ! count [3:0] $end
$var reg 1 " clk $end
$var reg 1 # rst $end
$var reg 1 $ up_down $end
$scope module dut $end
$var wire 1 " clk $end
$var wire 1 # rst $end
$var wire 1 $ up_down $end
$var reg 4 % count [3:0] $end
$upscope $end
$upscope $end
$enddefinitions $end
$comment Show the parameter values. $end
$dumpall
$end
#0
$dumpvars
bx %
1$
1#
0"
bx !
$end
#5000
b0 !
b0 %
1"
#10000
0"
0#
#15000
b1 !
b1 %
1"
#20000
0"
#25000
b10 !
b10 %
1"
#30000
0"
#35000
b11 !
b11 %
1"
#40000
0"
#45000
b100 !
b100 %
1"
#50000
0"
#55000
b101 !
b101 %
1"
#60000
0"
#65000
b110 !
b110 %
1"
#70000
0"
#75000
b111 !
b111 %
1"
#80000
0"
#85000
b1000 !
b1000 %
1"
#90000
0"
#95000
b1001 !
b1001 %
1"
#100000
0"
#105000
b1010 !
b1010 %
1"
#110000
0"
0$
#115000
b1001 !
b1001 %
1"
#120000
0"
#125000
b1000 !
b1000 %
1"
#130000
0"
#135000
b111 !
b111 %
1"
#140000
0"
#145000
b110 !
b110 %
1"
#150000
0"
#155000
b101 !
b101 %
1"
