t_flipflop/t_flipflop.v
module t_flipflop(t,clk,q,qbar);
input t,clk;
output reg q;
output qbar;

assign qbar = ~q;

always @(posedge clk)begin
    q <= ~t;
end
endmodule

t_flipflop/t_flipflop_tb.v
module t_flipflop_tb;

reg t,clk;
wire q,qbar;

t_flipflop uut( .t(t), .clk(clk), .q(q), .qbar(qbar));

always #05 clk = ~clk ;

initial begin
    $dumpfile("t_flipflop.vcd");
    $dumpvars(0,t_flipflop_tb);
    clk = 0;
    t = 0;#12;
    t = 1;#10;
    t = 0;#15;
    t = 1;#10;

    $finish;
end
endmodule

t_flipflop/t_flipflop.vcd
$date
	Sat Dec 20 12:42:19 2025
$end
$version
	Icarus Verilog
$end
$timescale
	1s
$end
$scope module t_flipflop_tb $end
$var wire 1 ! qbar $end
$var wire 1 " q $end
$var reg 1 # clk $end
$var reg 1 $ t $end
$scope module uut $end
$var wire 1 # clk $end
$var wire 1 ! qbar $end
$var wire 1 $ t $end
$var reg 1 " q $end
$upscope $end
$upscope $end
$enddefinitions $end
$comment Show the parameter values. $end
$dumpall
$end
#0
$dumpvars
0$
0#
x"
x!
$end
#5
0!
1"
1#
#10
0#
#12
1$
#15
1!
0"
1#
#20
0#
#22
0$
#25
0!
1"
1#
#30
0#
#35
1#
#37
1$
#40
0#
#45
1!
0"
1#
