FSM/vending_machine.v
module vending_machine (
    input clk,
    input reset,
    input [4:0] coin,      
    output reg dispense,
    output reg change
);
    
     parameter IDLE = 2'b00;
    parameter S10  = 2'b01;
    parameter S20  = 2'b10;
    parameter DISP = 2'b11;
    
    reg [1:0] current_state, next_state;

     reg give_change;


 
always @(posedge clk or posedge reset) begin
    if (reset) begin
        current_state <= IDLE;
        give_change   <= 1'b0;
    end 
    else begin
        current_state <= next_state;

         if (current_state == S20 && coin == 20)
            give_change <= 1'b1;

         else if (next_state == IDLE)
            give_change <= 1'b0;
    end
end


// --------------------------------------------------
// Combinational block: Next state logic
// --------------------------------------------------
always @(*) begin
    case (current_state)

        IDLE: begin
            if (coin == 10)      next_state = S10;
            else if (coin == 20) next_state = S20;
            else                 next_state = IDLE;
        end
        
        S10: begin
            if (coin == 10)      next_state = S20;
            else if (coin == 20) next_state = DISP;
            else                 next_state = S10;
        end
        
        S20: begin
            if (coin == 10)      next_state = DISP;
            else if (coin == 20) next_state = DISP;
            else                 next_state = S20;
        end
        
        DISP: next_state = IDLE;
        
        default: next_state = IDLE;
    endcase
end


 always @(*) begin
     dispense = 1'b0;
    change   = 1'b0;
    
    case (current_state)
        DISP: begin
            dispense = 1'b1;
            change   = give_change;   
        end
    endcase
end

endmodule

FSM/vending_machine_tb.v
module vending_machine_tb;
    reg clk;
    reg reset;
    reg [4:0] coin;

    wire dispense;
    wire change;

     vending_machine uut(clk,rst,coin,dispense,change);

     always #5 clk = ~clk;

     initial begin
        clk = 0;
        reset = 1;
        coin = 0;

     #10 reset = 0;

 
        #10 coin = 10;
        #10 coin = 0;    

        #20 coin = 10;
        #10 coin = 0;

         #30;

       
        #10 coin = 20;
        #10 coin = 0;

        #20 coin = 10;
        #10 coin = 0;

        #30;

       
        #10 coin = 20;
        #10 coin = 0;

        #20 coin = 20;
        #10 coin = 0;

        #30;

         $finish;
    end

     initial begin
        $dumpfile("dump.vcd");
        $dumpvars();
        $monitor("Time=%0t | coin=%0d | dispense=%b | change=%b",
                  $time, coin, dispense, change);
    end

endmodule

FSM/dump.vcd
$date
	Tue Mar  3 11:27:28 2026
$end
$version
	Icarus Verilog
$end
$timescale
	1s
$end
$scope module vending_machine_tb $end
$var wire 1 ! rst $end
$var wire 1 " dispense $end
$var wire 1 # change $end
$var reg 1 $ clk $end
$var reg 5 % coin [4:0] $end
$var reg 1 & reset $end
$scope module uut $end
$var wire 1 $ clk $end
$var wire 5 ' coin [4:0] $end
$var wire 1 ! reset $end
$var parameter 2 ( DISP $end
$var parameter 2 ) IDLE $end
$var parameter 2 * S10 $end
$var parameter 2 + S20 $end
$var reg 1 # change $end
$var reg 2 , current_state [1:0] $end
$var reg 1 " dispense $end
$var reg 1 - give_change $end
$var reg 2 . next_state [1:0] $end
$upscope $end
$upscope $end
$enddefinitions $end
$comment Show the parameter values. $end
$dumpall
b10 +
b1 *
b0 )
b11 (
$end
#0
$dumpvars
b0 .
x-
bx ,
b0 '
1&
b0 %
0$
x#
x"
z!
$end
#5
0#
0"
0-
b0 ,
1$
#10
0$
0&
#15
1$
#20
b1 .
0$
b1010 %
b1010 '
#25
b10 .
b1 ,
1$
#30
b1 .
0$
b0 %
b0 '
#35
1$
#40
0$
#45
1$
#50
b10 .
0$
b1010 %
b1010 '
#55
b11 .
b10 ,
1$
#60
b10 .
0$
b0 %
b0 '
#65
1$
#70
0$
#75
1$
#80
0$
#85
1$
#90
0$
#95
1$
#100
b11 .
0$
b10100 %
b10100 '
#105
1#
1"
b0 .
1-
b11 ,
1$
#110
0$
b0 %
b0 '
#115
0#
0"
0-
b0 ,
1$
#120
0$
#125
1$
#130
b1 .
0$
b1010 %
b1010 '
#135
b10 .
b1 ,
1$
#140
b1 .
0$
b0 %
b0 '
#145
1$
#150
0$
#155
1$
#160
0$
#165
1$
#170
0$
#175
1$
#180
b11 .
0$
b10100 %
b10100 '
#185
1"
b0 .
b11 ,
1$
#190
0$
b0 %
b0 '
#195
0"
b0 ,
1$
#200
0$
#205
1$
#210
b10 .
0$
b10100 %
b10100 '
#215
b11 .
b10 ,
1$
#220
b10 .
0$
b0 %
b0 '
