full_adder/full_adder.v
module full_adder(sum,carry,a,b,cin);
input a,b,cin;
output sum,carry;
assign sum = a ^ b ^ cin;
assign carry = (a & b) | (b & cin) | (a & cin);
endmodule

full_adder/full_adder_tb.v
module full_adder_tb;
reg a,b,cin;
wire sum,carry;
full_adder fa1(sum,carry,a,b,cin);
initial begin
    $dumpfile("dump.vcd");
    $dumpvars(0,full_adder_tb);
    $monitor("a=%b b=%b cin=%b sum=%b carry=%b",a,b,cin,sum,carry);
    a=0;b=0; cin=0; #10;
    a=0;b=1; cin=0; #10;              
    a=1;b=0; cin=0; #10;
    a=1;b=1; cin=0; #10;
    a=0;b=0; cin=1; #10;
    a=0;b=1; cin=1; #10;              
    a=1;b=0; cin=1; #10;
    a=1;b=1; cin=1; #10;

    $finish;

end
endmodule

full_adder/obj_dir/dump.vcd
$version Generated by VerilatedVcd $end
$timescale 1ps $end
 $scope module $rootio $end
 $upscope $end
 $scope module full_adder_tb $end
  $var wire 1 # a $end
  $var wire 1 $ b $end
  $var wire 1 % cin $end
  $var wire 1 & sum $end
  $var wire 1 ' carry $end
  $scope module fa1 $end
   $var wire 1 # a $end
   $var wire 1 $ b $end
   $var wire 1 % cin $end
   $var wire 1 & sum $end
   $var wire 1 ' carry $end
  $upscope $end
 $upscope $end
$enddefinitions $end


#0
0#
0$
0%
0&
0'
#10
1$
1&
#20
1#
0$
#30
1$
0&
1'
#40
0#
0$
1%
1&
0'
#50
1$
0&
1'
#60
1#
0$
#70
1$
1&
