8_1_mux/8_1_mux.v
module eight_one_mux(y,sel,in);
input[7:0]in;
input[2:0]sel;
output reg y;
always @(*)begin
    case (sel)
        3'b000: y=in[0];
        3'b001: y=in[1];
        3'b010: y=in[2];
        3'b011: y=in[3];
        3'b100: y=in[4];
        3'b101: y=in[5];
        3'b110: y=in[6];
        3'b111: y=in[7];
        default: y=1'bx;
    endcase
end
endmodule

8_1_mux/8_1_mux_tb.v
module eight_one_mux_tb();
reg[7:0]in;
reg[2:0]sel;
wire y;
eight_one_mux uut(.in(in),.sel(sel),.y(y));
initial begin
    in=8'b10101010; sel=3'b000; #10;
    in=8'b10101010; sel=3'b001; #10;
    in=8'b10101010; sel=3'b010; #10;
    in=8'b10101010; sel=3'b011; #10;
    in=8'b10101010; sel=3'b100; #10;
    in=8'b10101010; sel=3'b101; #10;
    in=8'b10101010; sel=3'b110; #10;
    in=8'b10101010; sel=3'b111; #10;
    $finish;
end
initial begin
    $monitor("in=%b sel=%b y=%b",in,sel,y);
    $dumpfile("dump.vcd");
    $dumpvars(0,eight_one_mux_tb);
end
endmodule

8_1_mux/dump.vcd
$date
	Mon Dec 29 19:02:32 2025
$end
$version
	Icarus Verilog
$end
$timescale
	1s
$end
$scope module eight_one_mux_tb $end
$var wire 1 ! y $end
$var reg 8 " in [7:0] $end
$var reg 3 # sel [2:0] $end
$scope module uut $end
$var wire 8 $ in [7:0] $end
$var wire 3 % sel [2:0] $end
$var reg 1 ! y $end
$upscope $end
$upscope $end
$enddefinitions $end
$comment Show the parameter values. $end
$dumpall
$end
#0
$dumpvars
b0 %
b10101010 $
b0 #
b10101010 "
0!
$end
#10
1!
b1 #
b1 %
#20
0!
b10 #
b10 %
#30
1!
b11 #
b11 %
#40
0!
b100 #
b100 %
#50
1!
b101 #
b101 %
#60
0!
b110 #
b110 %
#70
1!
b111 #
b111 %
