timer/timer_syn.v
module timer_syn (
    input clk,
    input rst,          // synchronous reset
    input start,
    input [7:0] load,
    output reg done
);

    reg [7:0] count;
    reg running;

    always @(posedge clk) begin
        if (rst) begin
            count   <= 8'd0;
            running <= 1'b0;
            done    <= 1'b0;
        end
        else begin
            // start pulse loads counter
            if (start && !running) begin
                count   <= load;
                running <= 1'b1;
                done    <= 1'b0;
            end

            // countdown
            else if (running) begin
                if (count == 8'd1) begin
                    count   <= 8'd0;
                    running <= 1'b0;
                    done    <= 1'b1;
                end
                else begin
                    count <= count - 1'b1;
                end
            end
        end
    end

endmodule

timer/timer_syn_tb.v
`timescale 1ns/1ps

module timer_tb;

    reg clk = 0;
    reg rst;
    reg start;
    reg [7:0] load;
    wire done;

    // Clock generation
    always #5 clk = ~clk;   // 10ns period

    timer_syn uut (
        .clk(clk),
        .rst(rst),
        .start(start),
        .load(load),
        .done(done)
    );

    initial begin

             $dumpfile("dump.vcd");
             $dumpvars();
             $monitor("clk = %b rst = %b start = %b load = %b done = %b",clk,rst,start,load,done);


        rst = 1;
        start = 0;
        load = 8'd10;

        #20 rst = 0;

        // Start timer
        #10 start = 1;
        #10 start = 0;

        // Wait and finish
        #200 $finish;
    end

endmodule

timer/dump.vcd
$date
	Thu Feb 19 19:51:15 2026
$end
$version
	Icarus Verilog
$end
$timescale
	1ps
$end
$scope module timer_tb $end
$var wire 1 ! done $end
$var reg 1 " clk $end
$var reg 8 # load [7:0] $end
$var reg 1 $ rst $end
$var reg 1 % start $end
$scope module uut $end
$var wire 1 " clk $end
$var wire 8 & load [7:0] $end
$var wire 1 $ rst $end
$var wire 1 % start $end
$var reg 8 ' count [7:0] $end
$var reg 1 ! done $end
$var reg 1 ( running $end
$upscope $end
$upscope $end
$enddefinitions $end
$comment Show the parameter values. $end
$dumpall
$end
#0
$dumpvars
x(
bx '
b1010 &
0%
1$
b1010 #
0"
x!
$end
#5000
0!
0(
b0 '
1"
#10000
0"
#15000
1"
#20000
0"
0$
#25000
1"
#30000
0"
1%
#35000
1(
b1010 '
1"
#40000
0"
0%
#45000
b1001 '
1"
#50000
0"
#55000
b1000 '
1"
#60000
0"
#65000
b111 '
1"
#70000
0"
#75000
b110 '
1"
#80000
0"
#85000
b101 '
1"
#90000
0"
#95000
b100 '
1"
#100000
0"
#105000
b11 '
1"
#110000
0"
#115000
b10 '
1"
#120000
0"
#125000
b1 '
1"
#130000
0"
#135000
1!
0(
b0 '
1"
