mst_sl_d_ff/design.v
module master_slave_ff(clk,rst,d,master,q);
input clk,d,rst;
output reg q;
output reg master;

always@(posedge clk,negedge rst) begin
  if(!rst) 
     master<=0;
  else
     master<=d;
end
always@(negedge clk,negedge rst)begin
 if(!rst)
    q<=0;
else
    q<=master;
end
endmodule

mst_sl_d_ff/tb.v
module tb();
reg clk,rst,d;
wire master,q;
master_slave_ff uut(clk,rst,d,master,q);

initial begin
   clk=0;
forever#5 clk=~clk;
end
initial begin
       $dumpfile("dump.vcd");
      $dumpvars(0,tb);
      $monitor("clk = %b rst = %b d = %b master = %b q = %b",clk,rst,d,master,q);

d=1;rst=1; #10
d=1;rst=0; #5
d=1;rst=1; #10
d=0;rst=1; #10
d=1;rst=1; #10
d=0;rst=1; #10
d=1;rst=1; #10
$finish;
end
endmodule

mst_sl_d_ff/dump.vcd
$date
	Thu Jan 29 21:05:50 2026
$end
$version
	Icarus Verilog
$end
$timescale
	1s
$end
$scope module tb $end
$var wire 1 ! q $end
$var wire 1 " master $end
$var reg 1 # clk $end
$var reg 1 $ d $end
$var reg 1 % rst $end
$scope module uut $end
$var wire 1 # clk $end
$var wire 1 $ d $end
$var wire 1 % rst $end
$var reg 1 " master $end
$var reg 1 ! q $end
$upscope $end
$upscope $end
$enddefinitions $end
$comment Show the parameter values. $end
$dumpall
$end
#0
$dumpvars
1%
1$
0#
x"
x!
$end
#5
1"
1#
#10
0!
0"
0#
0%
#15
1"
1#
1%
#20
1!
0#
#25
0"
1#
0$
#30
0!
0#
#35
1"
1#
1$
#40
1!
0#
#45
0"
1#
0$
#50
0!
0#
#55
1"
1#
1$
#60
1!
0#
