full_adder/full_adder.v
module full_adder(sum,carry,a,b,cin);
input a,b,cin;
output sum,carry;
assign sum = a ^ b ^ cin;
assign carry = (a & b) | (b & cin) | (a & cin);
endmodule

full_adder/full_adder_tb.v
module full_adder_tb;
reg a,b,cin;
wire sum,carry;
full_adder fa1(sum,carry,a,b,cin);
initial begin
    $dumpfile("dump.vcd");
    $dumpvars(0,full_adder_tb);
    $monitor("a=%b b=%b cin=%b sum=%b carry=%b",a,b,cin,sum,carry);
    a=0;b=0; cin=0; #10;
    a=0;b=1; cin=0; #10;              
    a=1;b=0; cin=0; #10;
    a=1;b=1; cin=0; #10;
    a=0;b=0; cin=1; #10;
    a=0;b=1; cin=1; #10;              
    a=1;b=0; cin=1; #10;
    a=1;b=1; cin=1; #10;

    $finish;

end
endmodule

full_adder/dump.vcd
$date
	Mon Dec 29 08:28:45 2025
$end
$version
	Icarus Verilog
$end
$timescale
	1s
$end
$scope module full_adder_tb $end
$var wire 1 ! sum $end
$var wire 1 " carry $end
$var reg 1 # a $end
$var reg 1 $ b $end
$var reg 1 % cin $end
$scope module fa1 $end
$var wire 1 # a $end
$var wire 1 $ b $end
$var wire 1 " carry $end
$var wire 1 % cin $end
$var wire 1 ! sum $end
$upscope $end
$upscope $end
$enddefinitions $end
$comment Show the parameter values. $end
$dumpall
$end
#0
$dumpvars
0%
0$
0#
0"
0!
$end
#10
1!
1$
#20
0$
1#
#30
1"
0!
1$
#40
0"
1!
1%
0$
0#
#50
1"
0!
1$
#60
0$
1#
#70
1!
1$
