four_by_two_mux/design.v
 module mux2_1 (
    input  i0,
    input  i1,
    input  sel,
    output y
);
    assign y = (~sel & i0) | (sel & i1);
endmodule


 
module mux4_1_using_2_1 (
    input        a,
    input        b,
    input        c,
    input        d,
    input  [1:0] sel,
    output       z
);

    wire y1, y2;

    mux2_1 m1 (.i0(a),  .i1(b),  .sel(sel[0]), .y(y1));
    mux2_1 m2 (.i0(c),  .i1(d),  .sel(sel[0]), .y(y2));
    mux2_1 m3 (.i0(y1), .i1(y2), .sel(sel[1]), .y(z));

endmodule

four_by_two_mux/tb.v
 
module tb_mux4_1;

    reg  a, b, c, d;
    reg  [1:0] sel;
    wire z;

     mux4_1_using_2_1 dut (
        .a(a), .b(b), .c(c), .d(d),
        .sel(sel),
        .z(z)
    );

    initial begin

        $dumpfile("mux4_1.vcd");
        $dumpvars(0, tb_mux4_1);
        $monitor("Time=%0t | sel=%b | a=%b b=%b c=%b d=%b | z=%b",
                  $time, sel, a, b, c, d, z);
         
         a = 0; b = 1; c = 0; d = 1;

        sel = 2'b00; #10;
        sel = 2'b01; #10;
        sel = 2'b10; #10;
        sel = 2'b11; #10;

         a = 1; b = 0; c = 1; d = 0;

        sel = 2'b00; #10;
        sel = 2'b01; #10;
        sel = 2'b10; #10;
        sel = 2'b11; #10;

        $finish;
    end

endmodule

four_by_two_mux/mux4_1.vcd
$date
	Mon Feb  9 20:56:46 2026
$end
$version
	Icarus Verilog
$end
$timescale
	1s
$end
$scope module tb_mux4_1 $end
$var wire 1 ! z $end
$var reg 1 " a $end
$var reg 1 # b $end
$var reg 1 $ c $end
$var reg 1 % d $end
$var reg 2 & sel [1:0] $end
$scope module dut $end
$var wire 1 " a $end
$var wire 1 # b $end
$var wire 1 $ c $end
$var wire 1 % d $end
$var wire 2 ' sel [1:0] $end
$var wire 1 ! z $end
$var wire 1 ( y2 $end
$var wire 1 ) y1 $end
$scope module m1 $end
$var wire 1 " i0 $end
$var wire 1 # i1 $end
$var wire 1 * sel $end
$var wire 1 ) y $end
$upscope $end
$scope module m2 $end
$var wire 1 $ i0 $end
$var wire 1 % i1 $end
$var wire 1 + sel $end
$var wire 1 ( y $end
$upscope $end
$scope module m3 $end
$var wire 1 ) i0 $end
$var wire 1 ( i1 $end
$var wire 1 , sel $end
$var wire 1 ! y $end
$upscope $end
$upscope $end
$upscope $end
$enddefinitions $end
$comment Show the parameter values. $end
$dumpall
$end
#0
$dumpvars
0,
0+
0*
0)
0(
b0 '
b0 &
1%
0$
1#
0"
0!
$end
#10
1!
1)
1(
1*
1+
b1 &
b1 '
#20
0!
0)
0(
0*
0+
1,
b10 &
b10 '
#30
1!
1)
1(
1*
1+
b11 &
b11 '
#40
1!
1(
1)
0*
0+
0,
b0 &
b0 '
0%
1$
0#
1"
#50
0!
0)
0(
1*
1+
b1 &
b1 '
#60
1!
1)
1(
0*
0+
1,
b10 &
b10 '
#70
0!
0)
0(
1*
1+
b11 &
b11 '
